Workbook
Name taxa_mensal: 'Página1'!$B$12
Name Aporte: 'Página1'!$B$10
Name redimento_carteira: 'Página1'!$E$11
Name qtd_anos: 'Página1'!$B$11

Sheet Página1
A9: INVESTIMENTO MENSAL | D9: Configurações
A10: Quanto investir por mês? | B10: 500 | D10: Salário | E10: 5000
A11: Por quantos anos? | B11: 5 | D11: Rendimento carteira | E11: 0.01
A12: Taxa de rendimento mensal? | B12: 0.01079 | D12: Sugestão investimento | E12: =E10*30% -> 1500
A13: Patrimônio acumulado? | B13: =FV(B12,B11*12,B10)*-1 -> 41888.457
A14: Dividendos mensais? | B14: =B13*E11 -> 418.88457
A16: Cenários | C16: Dividendos
A17: Quanto em 2 anos? | B17: =FV(B12,2*12,B10)*-1 -> 13613.814 | C17: =B17*redimento_carteira -> 136.13814
A18: Quanto em 5 anos? | B18: =B13 -> 41888.457 | C18: =B18*redimento_carteira -> 418.88457
A19: Quanto em 10 anos? | B19: =FV(B12,10*12,B10)*-1 -> 121642.11 | C19: =B19*redimento_carteira -> 1216.4211
A20: Quanto em 20 anos? | B20: =FV(B12,20*12,B10)*-1 -> 562599.2 | C20: =B20*redimento_carteira -> 5625.992
A21: Quanto em 30 anos? | B21: =FV(B12,30*12,B10)*-1 -> 2161084.8 | C21: =B21*redimento_carteira -> 21610.848
A23: Perfil | B23: Moderado
A24: Valor a ser investido por mês | B24: =Aporte -> 500
A26: TIPO DE FII | B26: Percentual Sugerido | C26: Valores
A27: PAPEL | B27: =VLOOKUP($B$23&"-"&A27,'Página2'!$A$1:$D$19,4,FALSE()) -> 0.32 | C27: =B27*$B$24 -> 160
A28: TIJOLO | B28: =VLOOKUP($B$23&"-"&A28,'Página2'!$A$1:$D$19,4,FALSE()) -> 0.35 | C28: =B28*$B$24 -> 175
A29: HÍBRIDOS | B29: =VLOOKUP($B$23&"-"&A29,'Página2'!$A$1:$D$19,4,FALSE()) -> 0.08 | C29: =B29*$B$24 -> 40
A30: FOFs | B30: =VLOOKUP($B$23&"-"&A30,'Página2'!$A$1:$D$19,4,FALSE()) -> 0.05 | C30: =B30*$B$24 -> 25
A31: DESENVOLVIMENTO | B31: =VLOOKUP($B$23&"-"&A31,'Página2'!$A$1:$D$19,4,FALSE()) -> 0.1 | C31: =B31*$B$24 -> 50
A32: HOTELARIAS | B32: =VLOOKUP($B$23&"-"&A32,'Página2'!$A$1:$D$19,4,FALSE()) -> 0.1 | C32: =B32*$B$24 -> 50
C33: =SUM(C27:C32) -> 500

Sheet Página2
A1: CHAVE | B1: PERFIL | C1: TIPO DE FII | D1: %
A2: =B2&"-"&C2 -> Conservador-PAPEL | B2: Conservador | C2: PAPEL | D2: 0.3
A3: =B3&"-"&C3 -> Conservador-TIJOLO | B3: Conservador | C3: TIJOLO | D3: 0.5
A4: =B4&"-"&C4 -> Conservador-HÍBRIDOS | B4: Conservador | C4: HÍBRIDOS | D4: 0.1
A5: =B5&"-"&C5 -> Conservador-FOFs | B5: Conservador | C5: FOFs | D5: 0.1
A6: =B6&"-"&C6 -> Conservador-DESENVOLVIMENTO | B6: Conservador | C6: DESENVOLVIMENTO | D6: 0
A7: =B7&"-"&C7 -> Conservador-HOTELARIAS | B7: Conservador | C7: HOTELARIAS | D7: 0
A8: =B8&"-"&C8 -> Moderado-PAPEL | B8: Moderado | C8: PAPEL | D8: 0.32
A9: =B9&"-"&C9 -> Moderado-TIJOLO | B9: Moderado | C9: TIJOLO | D9: 0.35
A10: =B10&"-"&C10 -> Moderado-HÍBRIDOS | B10: Moderado | C10: HÍBRIDOS | D10: 0.08
A11: =B11&"-"&C11 -> Moderado-FOFs | B11: Moderado | C11: FOFs | D11: 0.05
A12: =B12&"-"&C12 -> Moderado-DESENVOLVIMENTO | B12: Moderado | C12: DESENVOLVIMENTO | D12: 0.1
A13: =B13&"-"&C13 -> Moderado-HOTELARIAS | B13: Moderado | C13: HOTELARIAS | D13: 0.1
... A19: =B19&"-"&C19 -> Agressivo-HOTELARIAS | B19: Agressivo | C19: HOTELARIAS | D19: 0.1
